{
    "name": "Core\\Helper",
    "line": 12,
    "short_desc": "Helper and utility functions.",
    "long_desc": "",
    "hint": null,
    "tags": [],
    "namespace": "Core",
    "file": "\/Users\/chadchapman\/Repos\/chappy-php-framework\/src\/core\/Helper.php",
    "relative_file": null,
    "hash": "1e23c58659c46e0e3a0c97d156ac3eed6c6c6d0b",
    "parent": null,
    "modifiers": 0,
    "is_trait": false,
    "is_interface": false,
    "is_read_only": false,
    "aliases": {
        "Arr": "Core\\Lib\\Utilities\\Arr",
        "Env": "Core\\Lib\\Utilities\\Env",
        "ProfileImages": "Core\\Models\\ProfileImages",
        "AuthService": "Core\\Services\\AuthService"
    },
    "errors": [],
    "interfaces": [],
    "traits": [],
    "properties": [],
    "methods": {
        "buildMenuListItems": {
            "name": "buildMenuListItems",
            "line": 23,
            "short_desc": "Creates list of menu items.",
            "long_desc": "",
            "hint": [
                [
                    "Core\\string|false",
                    false
                ]
            ],
            "hint_desc": "Returns the contents of the active output buffer on\nsuccess or false on failure.",
            "tags": [],
            "see": [],
            "modifiers": 9,
            "is_by_ref": "",
            "is_intersection_type": false,
            "exceptions": [],
            "errors": [],
            "parameters": {
                "menu": {
                    "name": "menu",
                    "line": 23,
                    "short_desc": "The list of menu items containing the name and the\nURL path.",
                    "long_desc": null,
                    "hint": [
                        [
                            "array",
                            false
                        ]
                    ],
                    "tags": [],
                    "modifiers": 0,
                    "default": null,
                    "variadic": false,
                    "is_by_ref": false,
                    "is_read_only": false,
                    "is_intersection_type": false
                },
                "dropdownClass": {
                    "name": "dropdownClass",
                    "line": 23,
                    "short_desc": "The name of the classes that maybe set\ndepending on user input.",
                    "long_desc": null,
                    "hint": [
                        [
                            "string",
                            false
                        ]
                    ],
                    "tags": [],
                    "modifiers": 0,
                    "default": "\"\"",
                    "variadic": false,
                    "is_by_ref": false,
                    "is_read_only": false,
                    "is_intersection_type": false
                }
            }
        },
        "currentPage": {
            "name": "currentPage",
            "line": 71,
            "short_desc": "Determines current page based on REQUEST_URI.",
            "long_desc": "",
            "hint": [
                [
                    "Core\\string|null",
                    false
                ]
            ],
            "hint_desc": "$currentPage  The current page.",
            "tags": [],
            "see": [],
            "modifiers": 9,
            "is_by_ref": "",
            "is_intersection_type": false,
            "exceptions": [],
            "errors": [],
            "parameters": []
        },
        "getObjectProperties": {
            "name": "getObjectProperties",
            "line": 87,
            "short_desc": "Gets the properties of the given object",
            "long_desc": "",
            "hint": [
                [
                    "array",
                    false
                ]
            ],
            "hint_desc": "An associative array of defined object accessible\nnon-static properties for the specified object in scope. If a property\nhave not been assigned a value, it will be returned with a null value.",
            "tags": [],
            "see": [],
            "modifiers": 9,
            "is_by_ref": "",
            "is_intersection_type": false,
            "exceptions": [],
            "errors": [],
            "parameters": {
                "object": {
                    "name": "object",
                    "line": 87,
                    "short_desc": "An object instance.",
                    "long_desc": null,
                    "hint": [
                        [
                            "object",
                            false
                        ]
                    ],
                    "tags": [],
                    "modifiers": 0,
                    "default": null,
                    "variadic": false,
                    "is_by_ref": false,
                    "is_read_only": false,
                    "is_intersection_type": false
                }
            }
        },
        "getProfileImage": {
            "name": "getProfileImage",
            "line": 97,
            "short_desc": "Retrieves URL user's current profile image.",
            "long_desc": "",
            "hint": [
                [
                    "Core\\Core\\Models\\ProfileImages|false|null",
                    false
                ]
            ],
            "hint_desc": "The associative array for the profile image's\nrecord.",
            "tags": [],
            "see": [],
            "modifiers": 9,
            "is_by_ref": "",
            "is_intersection_type": false,
            "exceptions": [],
            "errors": [],
            "parameters": []
        }
    },
    "constants": []
}